smartML/__init__.py
smartML/algorithm/__init__.py
smartML/algorithm/algorithms.py
smartML/algorithm/regression.py
smartML/algorithm/tree_algorithm.py
smartML/dataset/__init__.py
smartML/dataset/data.py
smartML/validation/__init__.py
smartML/validation/cross_validation.py
smartML-0.1.10.dist-info/LICENSE
smartML-0.1.10.dist-info/METADATA
smartML-0.1.10.dist-info/WHEEL
smartML-0.1.10.dist-info/top_level.txt
smartML-0.1.10.dist-info/RECORD
