Metadata-Version: 2.1
Name: smartML
Version: 0.1.10
Summary: An ML library for various tasks!
Author: Şuayp Talha Kocabay
Author-email: kocabaysuayptalha08@gmail.com
Classifier: Programming Language :: Python :: 3
Classifier: Programming Language :: Python :: 3.8
Classifier: License :: OSI Approved :: MIT License
Classifier: Operating System :: OS Independent
Requires-Python: >=3.6
License-File: LICENSE
Requires-Dist: numpy
Requires-Dist: pandas
